qty.py
qty-0.0.2.dist-info/COPYING
qty-0.0.2.dist-info/WHEEL
qty-0.0.2.dist-info/METADATA
qty-0.0.2.dist-info/RECORD
