Metadata-Version: 2.1
Name: qty
Version: 0.0.2
Summary: A Python library for dealing with physical quantities
Home-page: https://gitlab.com/jdesch/qty
License: UNKNOWN
Author: Jude Deschamps
Author-email: jdesch@mit.edu
Requires-Python: >=3.6
Classifier: Intended Audience :: Science/Research
Classifier: License :: OSI Approved :: GNU General Public License v3 or later (GPLv3+)
Classifier: Topic :: Scientific/Engineering
Project-URL: Issues, https://gitlab.com/jdesch/qty/issues
Project-URL: Source, https://gitlab.com/jdesch/qty
